{
  "tasks": [
    {
      "task_title": "Setup DB",
      "parent_project": "proj_1",
      "due_date": "4/5/25",
      "project_dependencies": ["depend_1", "depend_2"],
      "task_score": 5,
      "task_match": 50,
      "task_id": 0,
      "task_status": "In Progress"
    },
    {
      "task_title": "Host site",
      "parent_project": "proj_1",
      "due_date": "4/6/25",
      "project_dependencies": ["depend_1", "depend_2"],
      "task_score": 7,
      "task_match": 80,
      "task_id": 1,
      "task_status": "In Progress"
    },
    {
      "task_title": "CI/CD",
      "parent_project": "proj_2",
      "due_date": "6/8/25",
      "project_dependencies": ["depend_1", "depend_2"],
      "task_score": 2,
      "task_match": 30,
      "task_id": 2,
      "task_status": "To Do"
    },
    {
      "task_title": "Unit Tests",
      "parent_project": "proj_2",
      "due_date": "5/6/25",
      "project_dependencies": ["depend_1", "depend_2"],
      "task_score": 9,
      "task_match": 40,
      "task_id": 3,
      "task_status": "To Do"
    },
    {
      "task_title": "Routes",
      "parent_project": "proj_4",
      "due_date": "4/5/25",
      "project_dependencies": ["depend_1", "depend_2"],
      "task_score": 5,
      "task_match": 50,
      "task_id": 4,
      "task_status": "In Progress"
    },
    {
      "task_title": "Presentation",
      "parent_project": "proj_4",
      "due_date": "4/5/25",
      "project_dependencies": ["depend_1", "depend_2"],
      "task_score": 5,
      "task_match": 50,
      "task_id": 4,
      "task_status": "To Do"
    }
  ]
}
